mlcvzoo_tf_classification/__init__.py
mlcvzoo_tf_classification/annotation_utils.py
mlcvzoo_tf_classification/base_model.py
mlcvzoo_tf_classification/configuration.py
mlcvzoo_tf_classification/const.py
mlcvzoo_tf_classification/custom_block/__init__.py
mlcvzoo_tf_classification/custom_block/configuration.py
mlcvzoo_tf_classification/custom_block/model.py
mlcvzoo_tf_classification/image_generator.py
mlcvzoo_tf_classification/py.typed
mlcvzoo_tf_classification/xception/__init__.py
mlcvzoo_tf_classification/xception/configuration.py
mlcvzoo_tf_classification/xception/model.py
mlcvzoo_tf_classification-6.0.3.dist-info/LICENSE
mlcvzoo_tf_classification-6.0.3.dist-info/METADATA
mlcvzoo_tf_classification-6.0.3.dist-info/WHEEL
mlcvzoo_tf_classification-6.0.3.dist-info/RECORD
